{"settings":[{"name":"emailShare","value":"Check out all there is to eat, drink, see and do during your visit to the Twin Cities.","notes":"Home page email share subject","airtableId":"rec9FroDQNF0ziJG3"},{"name":"facebookAccount","value":"startribune","notes":"Facebook account for FB sharing","airtableId":"rec1sbI14Dh9BdzXk"},{"name":"metaAuthor","value":"Star Tribune","notes":"Default author for meta tags","airtableId":"recodQDn1s5GLiU4S"},{"name":"metaDescription","value":"The Star Tribune's Essential Twin Cities guide is your complete guide to all there is to eat, drink, see and do during your visit to the Twin Cities.","notes":"Default description goes in meta tags and long social description, specifically for main page and any page that doesn't have one.","airtableId":"rec1yKm1FLEVLVjc5"},{"name":"metaKeywords","value":"twin cities, minnesota, minneapolis, st. paul, star tribune, restaurants, events, drinks, attractions","notes":"Default keywords for meta tags","airtableId":"recAE5ylRd1BQvYgf"},{"name":"organization","value":"Star Tribune","notes":"Used for meta data.","airtableId":"recYfvoJd61SjvN0P"},{"name":"shortTitle","value":"Twin Cities Guide","notes":"Short title specifically used when adding the site as an \"app\"","airtableId":"recLryLEJY1dFa9B2"},{"name":"title","value":"Essential Twin Cities Guide","notes":"Title for front page and suffix on all pages","airtableId":"recOoebsZxULAXSO4"},{"name":"twitterAccount","value":"StarTribune","notes":"Twitter account for twitter links","airtableId":"recNBKGSDlNeFlDcw"},{"name":"twitterShare","value":"Check out all there is to eat, drink, see and do during your visit to the Twin Cities.","notes":"Home page Twitter share text.","airtableId":"recnA0UE4QAHEpNjE"},{"name":"twitterShareDefault","notes":"Default Twitter text unless overrided","value":"I'm checking out [[NAME]] on the Star Tribune's Essential Twin Cities Guide","airtableId":"recLJ1MrzVrlTxG4A"}]}